phicloudmask/__init__.py
phicloudmask/constant.py
phicloudmask/embedding.py
phicloudmask/encoding.py
phicloudmask/main.py
phicloudmask/segmodel.py
phicloudmask-0.0.2.dist-info/LICENSE
phicloudmask-0.0.2.dist-info/WHEEL
phicloudmask-0.0.2.dist-info/METADATA
phicloudmask-0.0.2.dist-info/RECORD
