Metadata-Version: 2.1
Name: phicloudmask
Version: 0.0.2
Summary: Universal Cloud Mask Detector for Optical Remote Sensing Imagery
Home-page: https://github.com/csaybar/phicloudmask
Author: Cesar Aybar
Author-email: fcesar.aybar@uv.es
Requires-Python: >=3.9,<4.0
Classifier: Programming Language :: Python :: 3
Classifier: Programming Language :: Python :: 3.9
Classifier: Programming Language :: Python :: 3.10
Requires-Dist: einops (>=0.8.0)
Requires-Dist: numpy (>=1.25.2)
Requires-Dist: torch (>=2.0.0)
Requires-Dist: transformers (>=4.41.2)
Project-URL: Documentation, https://csaybar.github.io/phicloudmask/
Project-URL: Repository, https://github.com/csaybar/phicloudmask
